zarinpal_payment/__init__.py
zarinpal_payment/zarinpal.py
zarinpal_payment-0.0.7.dist-info/LICENSE
zarinpal_payment-0.0.7.dist-info/METADATA
zarinpal_payment-0.0.7.dist-info/WHEEL
zarinpal_payment-0.0.7.dist-info/top_level.txt
zarinpal_payment-0.0.7.dist-info/RECORD
