Metadata-Version: 2.2
Name: zarinpal-payment
Version: 0.0.7
Summary: a Python package for integrating the ZarinPal payment gateway.
Home-page: https://github.com/Mrj-Srb/zarinpal-payment-python
Author: Meraj Sarab
Author-email: srb.meraj@gmail.com
Project-URL: Author, https://github.com/Mrj-Srb
Classifier: Programming Language :: Python :: 3
Classifier: License :: OSI Approved :: MIT License
Classifier: Operating System :: OS Independent
Requires-Python: >=3.7
License-File: LICENSE
Requires-Dist: requests
Requires-Dist: logging
Dynamic: author
Dynamic: author-email
Dynamic: classifier
Dynamic: description
Dynamic: description-content-type
Dynamic: home-page
Dynamic: project-url
Dynamic: requires-dist
Dynamic: requires-python
Dynamic: summary
